Metadata-Version: 2.4
Name: rfdetr-isarsoft
Version: 1.1.0
Summary: RF-DETR
Author-email: Isarsoft GmbH <sarthak.trivedi@isarsoft.com>
License: Apache License 2.0
Project-URL: Homepage, https://github.com/roboflow/rf-detr
Keywords: machine-learning,deep-learning,vision,ML,DL,AI,DETR,RF-DETR,Roboflow
Classifier: Development Status :: 4 - Beta
Classifier: Intended Audience :: Developers
Classifier: Intended Audience :: Education
Classifier: Intended Audience :: Science/Research
Classifier: License :: OSI Approved :: Apache Software License
Classifier: Programming Language :: Python :: 3
Classifier: Programming Language :: Python :: 3.9
Classifier: Programming Language :: Python :: 3.10
Classifier: Programming Language :: Python :: 3.11
Classifier: Programming Language :: Python :: 3.12
Classifier: Programming Language :: Python :: 3.13
Classifier: Programming Language :: Python :: 3 :: Only
Classifier: Topic :: Software Development
Classifier: Topic :: Scientific/Engineering
Classifier: Topic :: Scientific/Engineering :: Artificial Intelligence
Classifier: Typing :: Typed
Classifier: Operating System :: POSIX
Classifier: Operating System :: Unix
Classifier: Operating System :: MacOS
Requires-Python: >=3.9
License-File: LICENSE
Requires-Dist: cython
Requires-Dist: pycocotools
Requires-Dist: torch>=1.13.0
Requires-Dist: torchvision>=0.14.0
Requires-Dist: fairscale
Requires-Dist: scipy
Requires-Dist: timm
Requires-Dist: tqdm
Requires-Dist: numpy
Requires-Dist: accelerate
Requires-Dist: transformers
Requires-Dist: peft
Requires-Dist: ninja
Requires-Dist: einops
Requires-Dist: pandas
Requires-Dist: pylabel
Requires-Dist: polygraphy
Requires-Dist: open_clip_torch
Requires-Dist: rf100vl
Requires-Dist: pydantic
Requires-Dist: supervision
Requires-Dist: matplotlib
Provides-Extra: onnxexport
Requires-Dist: onnx; extra == "onnxexport"
Requires-Dist: onnxsim; extra == "onnxexport"
Requires-Dist: onnx_graphsurgeon; extra == "onnxexport"
Requires-Dist: onnxruntime; extra == "onnxexport"
Provides-Extra: metrics
Requires-Dist: tensorboard>=2.13.0; extra == "metrics"
Requires-Dist: wandb; extra == "metrics"
Provides-Extra: build
Requires-Dist: twine>=5.1.1; extra == "build"
Requires-Dist: wheel>=0.40; extra == "build"
Requires-Dist: build>=0.10; extra == "build"
Dynamic: license-file
